gkhtm/HTMCircleAllIDsCassandra.cpp
gkhtm/HTMCircleAllIDsCassandra.h
gkhtm/HTMCircleRegion.cpp
gkhtm/HTMCircleRegion.h
gkhtm/__init__.py
gkhtm/__version__.py
gkhtm/_gkhtm.cpython-38-darwin.so
gkhtm/build.sh
gkhtm/clean.sh
gkhtm/gkhtm.i
gkhtm/htm/Makefile.generic
gkhtm/htm/README.txt
gkhtm/htm/READ_ME
gkhtm/htm/build.sh
gkhtm/htm/cc_aux.c
gkhtm/htm/configure
gkhtm/htm/darwin.sed
gkhtm/htm/domain
gkhtm/htm/env_macos.sh
gkhtm/htm/htmid.C
gkhtm/htm/linux.sed
gkhtm/htm/testme.C
gkhtm/htm/app/.gdb_history
gkhtm/htm/app/echoDomain.cpp
gkhtm/htm/app/example.cpp
gkhtm/htm/app/fillout.c
gkhtm/htm/app/htmTest.cpp
gkhtm/htm/app/htmlookup.c
gkhtm/htm/app/intersect.cpp
gkhtm/htm/app/lookup.cpp
gkhtm/htm/app/range2list.c
gkhtm/htm/app/sqlExample.cpp
gkhtm/htm/app/sqlExample0.cpp
gkhtm/htm/app/test1.cpp
gkhtm/htm/app/timeHTM.cpp
gkhtm/htm/app/toid.c
gkhtm/htm/app/toname.c
gkhtm/htm/app/xptest.cpp
gkhtm/htm/include/Convexio.h
gkhtm/htm/include/HtmRange.h
gkhtm/htm/include/HtmRangeIterator.h
gkhtm/htm/include/Htmio.h
gkhtm/htm/include/RangeConvex.h
gkhtm/htm/include/RangeConvex.hxx
gkhtm/htm/include/SkipList.h
gkhtm/htm/include/SkipListElement.h
gkhtm/htm/include/SpatialConstraint.h
gkhtm/htm/include/SpatialConstraint.hxx
gkhtm/htm/include/SpatialConvex.hxx
gkhtm/htm/include/SpatialDoc.h
gkhtm/htm/include/SpatialDomain.bak_h
gkhtm/htm/include/SpatialDomain.h
gkhtm/htm/include/SpatialDomain.hxx
gkhtm/htm/include/SpatialEdge.h
gkhtm/htm/include/SpatialException.h
gkhtm/htm/include/SpatialGeneral.h
gkhtm/htm/include/SpatialIndex.h
gkhtm/htm/include/SpatialIndex.hxx
gkhtm/htm/include/SpatialInterface.h
gkhtm/htm/include/SpatialInterface.hxx
gkhtm/htm/include/SpatialSign.h
gkhtm/htm/include/SpatialVector.h
gkhtm/htm/include/SpatialVector.hxx
gkhtm/htm/include/VarCmp.h
gkhtm/htm/include/VarStr.h
gkhtm/htm/include/VarStr.hpp
gkhtm/htm/include/VarStr.hxx
gkhtm/htm/include/sqlInterface.h
gkhtm/htm/include/sqlInterface.hxx
gkhtm/htm/include/srv.h
gkhtm/htm/include/swapper
gkhtm/htm/perl/HTM.bs
gkhtm-0.0.10.dist-info/LICENSE
gkhtm-0.0.10.dist-info/METADATA
gkhtm-0.0.10.dist-info/WHEEL
gkhtm-0.0.10.dist-info/top_level.txt
gkhtm-0.0.10.dist-info/RECORD
